kv_client_wrappers-0.0.1.dist-info/licenses/LICENSE
kv_store/__init__.py
kv_store/base.py
kv_store/memory.py
kv_store/redis.py
kv_client_wrappers-0.0.1.dist-info/METADATA
kv_client_wrappers-0.0.1.dist-info/WHEEL
kv_client_wrappers-0.0.1.dist-info/top_level.txt
kv_client_wrappers-0.0.1.dist-info/RECORD
