Metadata-Version: 2.4
Name: kv-client-wrappers
Version: 0.0.1
Summary: A simple wrapper for key-value stores supporting Python dict, Redis, Valkey, Memcached, and SQLite and other backend clients.
Author-email: Gaioz Tabatadze <tabatadzegaga@gmail.com>
Project-URL: Homepage, https://github.com/qaioz/kv-store
Classifier: Development Status :: 3 - Alpha
Classifier: Intended Audience :: Developers
Classifier: License :: OSI Approved :: MIT License
Classifier: Operating System :: OS Independent
Classifier: Programming Language :: Python
Classifier: Programming Language :: Python :: 3
Classifier: Programming Language :: Python :: 3.10
Classifier: Programming Language :: Python :: 3.11
Classifier: Programming Language :: Python :: 3.12
Classifier: Programming Language :: Python :: 3.13
Classifier: Topic :: Database
Classifier: Topic :: Database :: Database Engines/Servers
Classifier: Topic :: Database :: Front-Ends
Classifier: Topic :: Software Development :: Libraries
Classifier: Topic :: Software Development :: Libraries :: Python Modules
Classifier: Topic :: System :: Distributed Computing
Classifier: Topic :: Utilities
Classifier: Topic :: Software Development :: Libraries :: Application Frameworks
Requires-Python: >=3.10
License-File: LICENSE
Requires-Dist: pytest>=9.0.2
Requires-Dist: pytest-asyncio>=1.3.0
Requires-Dist: redis>=7.1.0
Dynamic: license-file
